clash_config_preprocessor/__init__.py
clash_config_preprocessor/cli.py
clash_config_preprocessor/utils.py
clash_config_preprocessor/v1.py
clash_config_preprocessor/v2.py
clash_config_preprocessor-0.1.4.dist-info/entry_points.txt
clash_config_preprocessor-0.1.4.dist-info/LICENSE
clash_config_preprocessor-0.1.4.dist-info/WHEEL
clash_config_preprocessor-0.1.4.dist-info/METADATA
clash_config_preprocessor-0.1.4.dist-info/RECORD
